howmuchtime/__init__.py
howmuchtime/hmt.py
howmuchtime-0.2.0.dist-info/DESCRIPTION.rst
howmuchtime-0.2.0.dist-info/METADATA
howmuchtime-0.2.0.dist-info/RECORD
howmuchtime-0.2.0.dist-info/WHEEL
howmuchtime-0.2.0.dist-info/entry_points.txt
howmuchtime-0.2.0.dist-info/metadata.json
howmuchtime-0.2.0.dist-info/top_level.txt
