Metadata-Version: 2.0
Name: howmuchtime
Version: 0.2.0
Summary: Countdown to a date.
Home-page: https://github.com/FilipOsowski/howmuchtime
Author: Filip Osowski
Author-email: filiposowski5@gmail.com
License: MIT
Platform: UNKNOWN
Classifier: Development Status :: 3 - Alpha
Classifier: Programming Language :: Python :: 3
Requires-Python: ~=3.0
